setup.py
gaussian_binominal_distributions.egg-info/PKG-INFO
gaussian_binominal_distributions.egg-info/SOURCES.txt
gaussian_binominal_distributions.egg-info/dependency_links.txt
gaussian_binominal_distributions.egg-info/not-zip-safe
gaussian_binominal_distributions.egg-info/top_level.txt
l0ltestpypi/Binomialdistribution.py
l0ltestpypi/Gaussiandistribution.py
l0ltestpypi/Generaldistribution.py
l0ltestpypi/__init__.py
l0ltestpypi/setup.py