Metadata-Version: 1.0
Name: gaussian-binominal-distributions
Version: 0.1
Summary: Gaussian & Binominal distributions
Home-page: UNKNOWN
Author: UNKNOWN
Author-email: UNKNOWN
License: UNKNOWN
Platform: UNKNOWN
